signipy/__init__.py
signipy-1.1.0.dist-info/LICENSE
signipy-1.1.0.dist-info/METADATA
signipy-1.1.0.dist-info/WHEEL
signipy-1.1.0.dist-info/top_level.txt
signipy-1.1.0.dist-info/RECORD
