Metadata-Version: 2.1
Name: signipy
Version: 1.1.0
Summary: A simple python library for System Functions.
Home-page: 
Author: vyzv
Author-email: lovebotter01@gmail.com
License: MIT
Keywords: system
Classifier: Development Status :: 5 - Production/Stable
Classifier: Intended Audience :: Education
Classifier: Operating System :: Microsoft :: Windows :: Windows 10
Classifier: License :: OSI Approved :: MIT License
Classifier: Programming Language :: Python :: 3
License-File: LICENSE
